Workbook

Sheet 1. Assumptions
A1: LCoE inputs — hybrid geothermal heating & cooling system
A2: Blue text on yellow = inputs (change these for scenarios). Black text = calculated. Documented sources in column D.
A4: System design
A5: Heating demand peak | B5: 10 | C5: MWth | D5: Challenge brief minimum
A6: Cooling demand peak | B6: 5 | C6: MWth | D6: Challenge brief minimum
A7: Heating FLEH | B7: 2400 | C7: hr/yr | D7: NL DHC typical
A8: Cooling FLEH | B8: 1500 | C8: hr/yr | D8: NL summer cooling demand
A9: Project lifetime | B9: 25 | C9: years | D9: Geothermal industry standard
A10: Discount rate | B10: 0.07 | C10: fraction | D10: NL geothermal WACC ~7%
A12: Geothermal doublet (BLT-01 producer + USP-01 injector)
A13: Production flow rate | B13: 105 | C13: m³/h | D13: BLT-01 ThermoGIS P50
A14: Production temperature | B14: 77 | C14: °C | D14: BLT-01 ThermoGIS
A15: Injection temperature (after HP-1) | B15: 15 | C15: °C | D15: After return-brine HP
A16: Brine density | B16: 1000 | C16: kg/m³
A17: Brine specific heat | B17: 4180 | C17: J/kg·K
A18: Mass flow rate | B18: =B13/3600*B16 | C18: kg/s | D18: flow / 3600 × density
A19: Direct geothermal heat | B19: =B18*B17*(B14-35)/1000000 | C19: MWth | D19: Brine 77→35 °C (before HP-1)
A21: Heat pumps
A22: HP-1 COP (return brine 35→15 °C) | B22: 3.5 | D22: Typical 70 °C sink
A23: HP-1 heat extracted from brine | B23: =B18*B17*(35-B15)/1000000 | C23: MW | D23: Brine 35→15 °C
A24: HP-1 electricity input | B24: =B23/(B22-1) | C24: MW | D24: W = Qcold/(COP-1)
A25: HP-1 heat output | B25: =B22*B24 | C25: MWth
A26: HP-2 COP (ATES warm well) | B26: 4 | D26: Better source temp
A27: HP-2 heat output | B27: 2.17 | C27: MWth | D27: Sized per design doc
A28: HP-2 electricity input | B28: =B27/B26 | C28: MW
A30: Total heating capacity | B30: =B19+B25+B27 | C30: MWth
A31: Total heating electricity | B31: =B24+B28 | C31: MW
A33: Cooling
A34: Absorption chiller capacity | B34: 3 | C34: MWth | D34: Single-effect LiBr
A35: Absorption chiller COP | B35: 0.7
A36: Electric chiller capacity | B36: 2 | C36: MWth | D36: Peaking unit
A37: Electric chiller COP | B37: 5
A38: ATES cold well capacity | B38: 1 | C38: MWth | D38: Passive cooling
A39: Total cooling capacity | B39: =B34+B36+B38 | C39: MWth

Sheet 2. CapEx
A1: Capital expenditure breakdown
A3: Item | B3: Cost (€M) | C3: % | D3: Source
A4: Subsurface
A5: Drilling USP-01 (1 new well, ~1830 m TVD) | B5: 5 | D5: €2.5M base + €1500/m for depth
A6: Workover BLT-01 (recompletion as producer) | B6: 1 | D6: NL geothermal benchmark
A7: Reservoir engineering + permitting | B7: 0.5 | D7: TNO advisory + EBN approval
A8: Surface plant
A9: Plant building + civil works | B9: 2 | D9: Industrial benchmark
A10: Primary heat exchanger (corrosion-resistant) | B10: 1 | D10: Duplex SS, brine duty
A11: Heat pump HP-1 (~1 MW electric) | B11: 0.8 | D11: Industrial HP, €800/kW
A12: Heat pump HP-2 (~0.5 MW electric) | B12: 0.5 | D12: Smaller unit
A13: Absorption chiller (3 MW) | B13: 1 | D13: LiBr, €330/kW cooling
A14: Electric chiller (2 MW) | B14: 0.5 | D14: Vapor-compression
A15: Pumps, control, BoP | B15: 1 | D15: ~5% of plant
A16: ATES system
A17: Warm well + cold well drilling | B17: 1.5 | D17: 2 × ~150 m wells, €750k ea.
A18: ATES pumps, HX, heat exchanger | B18: 0.5 | D18: Standard ATES skid
A19: Pipelines
A20: Hot brine line BLT-01 → plant (2.0 km) | B20: 2 | D20: €1M/km insulated
A21: Cool brine line plant → USP-01 (0.5 km) | B21: 0.3 | D21: Less insulation
A22: District network (5 km, primary loop) | B22: 3 | D22: €600/m district
A23: Other
A24: Contingency (15%) | B24: =SUM(B5:B23)*0.15 | D24: 15% of subtotal
A25: TOTAL CAPEX | B25: =SUM(B5:B23)+B24
A27: CapEx unit metrics
A28: CapEx per MW thermal (combined) | B28: =B25/('1. Assumptions'!B5+'1. Assumptions'!B6) | C28: €M/MWth

Sheet 3. OpEx
A1: Operating expenditure (annual)
A3: Item | B3: Annual (€k/yr) | C3: % | D3: Basis
A5: Electricity inputs
A6: Heating electricity (HP-1 + HP-2, winter) | B6: 5500 | C6: MWh/yr | D6: See design doc §4
A7: Cooling electricity (EC + auxiliaries) | B7: 1000 | C7: MWh/yr | D7: Summer chiller + pumps
A8: Doublet pump + district circulation | B8: 2250 | C8: MWh/yr | D8: Year-round
A9: Total electricity | B9: =SUM(B6:B8) | C9: MWh/yr
A11: NL industrial electricity price | B11: 100 | C11: €/MWh | D11: NL 2024 industrial avg incl. taxes
A12: Electricity annual cost | B12: =B9*B11/1000 | C12: €k/yr
A14: Other operating costs
A15: Maintenance (% of CapEx) | B15: 0.025 | D15: NL geothermal benchmark 2-3%
A16: Maintenance cost | B16: =B15*'2. CapEx'!B25*1000 | C16: €k/yr
A17: Labour + monitoring + insurance | B17: 250 | C17: €k/yr | D17: 2 FTE + supervisory + insurance
A18: Reservoir monitoring (chemistry, pressure) | B18: 100 | C18: €k/yr | D18: EBN regulatory requirement
A20: Total annual OpEx
A21: Total OpEx | B21: =B12+B16+B17+B18 | C21: €k/yr

Sheet 4. Energy delivered
A1: Annual energy delivered
A3: Item | B3: Value | C3: Unit | D3: Calculation
A5: Heating delivered | B5: ='1. Assumptions'!B5*'1. Assumptions'!B7 | C5: MWh/yr | D5: peak heating × FLEH heating
A6: Cooling delivered | B6: ='1. Assumptions'!B6*'1. Assumptions'!B8 | C6: MWh/yr | D6: peak cooling × FLEH cooling
A7: Total useful energy | B7: =B5+B6 | C7: MWh/yr
A9: Total electricity consumed | B9: ='3. OpEx'!B9 | C9: MWh/yr
A10: System SPF (seasonal performance factor) | B10: =B7/B9 | C10: – | D10: Useful energy / electricity in
A12: CO₂ avoided
A13: Gas emission factor displaced | B13: 0.2 | C13: tCO₂/MWh
A14: NL grid electricity emission factor | B14: 0.25 | C14: tCO₂/MWh | D14: 2026 NL grid average
A15: Gross CO₂ displaced (no gas burned) | B15: =B5*B13 | C15: tCO₂/yr
A16: CO₂ from electricity used | B16: =B9*B14 | C16: tCO₂/yr
A17: Net CO₂ avoided | B17: =B15-B16 | C17: tCO₂/yr

Sheet 5. LCoE
A1: Levelized Cost of Energy (LCoE)
A2: LCoE = (CapEx × CRF + OpEx) / annual energy delivered
A4: Component | B4: Value | C4: Unit
A6: Discount rate (r) | B6: ='1. Assumptions'!B10 | C6: –
A7: Lifetime (n) | B7: ='1. Assumptions'!B9 | C7: years
A8: Capital recovery factor (CRF) | B8: =B6/(1-(1+B6)^-B7) | C8: –
A10: Total CapEx | B10: ='2. CapEx'!B25 | C10: €M
A11: Annualized CapEx (CapEx × CRF) | B11: =B10*B8 | C11: €M/yr
A12: Annual OpEx | B12: ='3. OpEx'!B21/1000 | C12: €M/yr
A13: Total annual cost | B13: =B11+B12 | C13: €M/yr
A15: Annual energy delivered | B15: ='4. Energy delivered'!B7 | C15: MWh/yr
A17: LCoE | B17: =B13*1000000/B15 | C17: €/MWh
A18: LCoE in €/kWh | B18: =B17/1000 | C18: €/kWh
A20: Benchmarks (NL onshore geothermal direct use)
A21: EBN/TNO 2020-2024 reported LCoE for NL geothermal: €60-€120/MWh (heat only).
A22: Hybrid systems with heat pumps + cooling typically €80-€140/MWh due to higher CapEx but additional revenue stream.

Sheet 6. Sensitivity
A1: Sensitivity analysis — LCoE swing per ±20% input change
A2: Computed from the shared LCoE model (03_analysis/scripts/lcoe_model.py) — the same model used by the sensitivity tornado notebook and the Monte Carlo. One input is changed at a time from the Assumptions base case (base LCoE ≈ €122/MWh).
A4: Input | B4: Base value | C4: Low (-20%) | D4: High (+20%) | E4: ΔLCoE (low) | F4: ΔLCoE (high)
A5: Drilling cost (€M/well) | B5: 5 | C5: 4 | D5: 6 | E5: -€4.0/MWh | F5: +€4.0/MWh
A6: NL electricity price (€/MWh) | B6: 100 | C6: 80 | D6: 120 | E6: -€5.6/MWh | F6: +€5.6/MWh
A7: Discount rate | B7: 0.07 | C7: 0.056 | D7: 0.084 | E7: -€7.9/MWh | F7: +€8.3/MWh
A8: Heating FLEH (hr/yr) | B8: 2400 | C8: 1920 | D8: 2880 | E8: +€19.6/MWh | F8: -€14.4/MWh
A9: HP-1 COP | B9: 3.5 | C9: 2.8 | D9: 4.2 | E9: +€1.9/MWh | F9: -€1.2/MWh
A10: Project lifetime (years) | B10: 25 | C10: 20 | D10: 30 | E10: +€6.5/MWh | F10: -€3.9/MWh
A11: USP-01 production (% of P50) | B11: 1 | C11: 0.8 | D11: 1.2 | E11: +€2.4/MWh | F11: -€0.5/MWh
A14: Biggest sensitivity by far is heating utilisation (FLEH), then the financing-side levers (discount rate, project lifetime). Doublet flow rate and HP-1 COP are minor LCoE levers within ±20% because the heat pumps efficiently absorb a geothermal shortfall while pumping electricity falls; the material USP-01 risk is the discontinuous case (missing peak demand / needing a second doublet), not a ±20% LCoE gradient.
